tests/__init__.py
tests/test_datasets.py
tests/test_facilities.py
tests/test_probes.py
tests/test_spectrometers.py
usnan/__init__.py
usnan/client.py
usnan/endpoints/__init__.py
usnan/endpoints/base.py
usnan/endpoints/datasets.py
usnan/endpoints/facilities.py
usnan/endpoints/probes.py
usnan/endpoints/spectrometers.py
usnan/models/__init__.py
usnan/models/datasets.py
usnan/models/facilities.py
usnan/models/probes.py
usnan/models/search.py
usnan/models/spectrometers.py
usnan-0.2.dist-info/METADATA
usnan-0.2.dist-info/WHEEL
usnan-0.2.dist-info/top_level.txt
usnan-0.2.dist-info/RECORD
